LICENSE
MANIFEST.in
README.md
setup.cfg
setup.py
simpletraj/__init__.py
simpletraj/trajectory.py
simpletraj.egg-info/PKG-INFO
simpletraj.egg-info/SOURCES.txt
simpletraj.egg-info/dependency_links.txt
simpletraj.egg-info/not-zip-safe
simpletraj.egg-info/pbr.json
simpletraj.egg-info/requires.txt
simpletraj.egg-info/top_level.txt
simpletraj/dcd/__init__.py
simpletraj/dcd/dcd.c
simpletraj/dcd/dcd.py
simpletraj/dcd/include/correl.h
simpletraj/dcd/include/endianswap.h
simpletraj/dcd/include/fastio.h
simpletraj/dcd/include/readdcd.h
simpletraj/xdrfile/__init__.py
simpletraj/xdrfile/libxdrfile2.py
simpletraj/xdrfile/libxdrfile2_wrap.c
simpletraj/xdrfile/xdrfile.c
simpletraj/xdrfile/xdrfile.h
simpletraj/xdrfile/xdrfile_trr.c
simpletraj/xdrfile/xdrfile_trr.h
simpletraj/xdrfile/xdrfile_xtc.c
simpletraj/xdrfile/xdrfile_xtc.h
test/test_trajectory.py